pytest_maybe_context/__init__.py
pytest_maybe_context/main.py
pytest_maybe_context/py.typed
pytest_maybe_context-0.1.dist-info/METADATA
pytest_maybe_context-0.1.dist-info/WHEEL
pytest_maybe_context-0.1.dist-info/RECORD
