Metadata-Version: 2.1
Name: pytest-maybe-context
Version: 0.1
Summary: Simplify tests with warning and exception cases.
Home-page: https://github.com/wrwrwr/pytest-maybe-context
License: MIT
Keywords: pytest,plugin
Author: wrwrwr
Author-email: code@wr.waw.pl
Requires-Python: >=3.10,<4.0
Classifier: License :: OSI Approved :: MIT License
Classifier: Programming Language :: Python :: 3
Classifier: Programming Language :: Python :: 3.10
Classifier: Programming Language :: Python :: 3.11
Requires-Dist: pytest (>=7,<8)
Project-URL: Repository, https://github.com/wrwrwr/pytest-maybe-context
